{
	"display": {
		"icon": {
			"item": "minecraft:purpur_block"
		},
		"title": {
			"text": "Purpur Block",
			"color": "aqua"
		},
		"description": {
			"text": "Obtenir un(e) Purpur Block",
			"color": "gray"
		},
		"frame": "task",
		"show_toast": false,
		"announce_to_chat": false,
		"hidden": false
	},
	"criteria": {
		"requirement": {
			"trigger": "minecraft:inventory_changed",
			"conditions": {
				"items": [
					{
						"items": [
							"minecraft:purpur_block"
						]
					}
				]
			}
		}
	},
	"requirements": [
		[
			"requirement"
		]
	]
}
